tree_lstm/__init__.py
tree_lstm/tree_lstm.py
tree_lstm-0.0.8.dist-info/LICENSE
tree_lstm-0.0.8.dist-info/METADATA
tree_lstm-0.0.8.dist-info/WHEEL
tree_lstm-0.0.8.dist-info/top_level.txt
tree_lstm-0.0.8.dist-info/RECORD
