Metadata-Version: 2.1
Name: tree-lstm
Version: 0.0.8
Summary: pytorch tree lstm package
Home-page: https://github.com/inyukwo1/tree-lstm
Author: Inhyuk Na
Author-email: ina@dblab.postech.ac.kr
License: UNKNOWN
Platform: UNKNOWN
Classifier: Programming Language :: Python :: 3
Classifier: License :: OSI Approved :: MIT License
Classifier: Operating System :: OS Independent
Requires-Dist: torch
Requires-Dist: dgl
